blup/__main__.py
blup/blup_loader.py
blup/exceptions.py
blup-1.1.dist-info/METADATA
blup-1.1.dist-info/WHEEL
blup-1.1.dist-info/entry_points.txt
blup-1.1.dist-info/top_level.txt
blup-1.1.dist-info/RECORD
