Metadata-Version: 2.1
Name: blup
Version: 1.1
Summary: Turn JSON into HTML using Jinja
Home-page: https://github.com/16arpi/blup
Author: César Pichon
License: GPL-3.0
Requires-Dist: jinja2
